LICENSE
MANIFEST.in
README.txt
setup.py
docs/Cправка_arraypy+tensor_methods.doc
docs/Help_arraypy+tensor_methods.doc
docs/Help_riemannian_geometry.doc
docs/Help_tensor_fields.doc
docs/Справка_riemannian_geometry.doc
docs/Справка_tensor_fields.doc
tensor_analysis/__init__.py
tensor_analysis/arraypy.py
tensor_analysis/helper_functions.py
tensor_analysis/riemannian_geometry.py
tensor_analysis/tensor_fields.py
tensor_analysis/tensor_methods.py
tensor_analysis.egg-info/PKG-INFO
tensor_analysis.egg-info/SOURCES.txt
tensor_analysis.egg-info/dependency_links.txt
tensor_analysis.egg-info/requires.txt
tensor_analysis.egg-info/top_level.txt
tensor_analysis/tests/__init__.py
tensor_analysis/tests/test_arraypy.py
tensor_analysis/tests/test_riemannian_geometry.py
tensor_analysis/tests/test_tensor_fields.py
tensor_analysis/tests/test_tensor_methods.py
tensor_analysis/tests/__init__.py
tensor_analysis/tests/test_arraypy.py
tensor_analysis/tests/test_riemannian_geometry.py
tensor_analysis/tests/test_tensor_fields.py
tensor_analysis/tests/test_tensor_methods.py