Metadata-Version: 1.1
Name: tensor-analysis
Version: 1.0.1
Summary: Tensor analysis package for n-dimensional tensor calculation
Home-page: https://github.com/AunShiLord/Tensor-analysis.git
Author: Vladimir Kuzmin, Konovalenko Anastasia, Merzlyakova Ksenia
Author-email: aunshilord@yahoo.com
License: UNKNOWN
Keywords: tensor,tensor_fields,riemannian,arraypy,sympy,tensor_algebra
Platform: UNKNOWN
Classifier: Programming Language :: Python
Classifier: Programming Language :: Python :: 2
Classifier: Programming Language :: Python :: 2.6
Classifier: Programming Language :: Python :: 2.7
Classifier: Programming Language :: Python :: 3
Classifier: Programming Language :: Python :: 3.2
Classifier: Programming Language :: Python :: 3.3
Classifier: Programming Language :: Python :: 3.4
Classifier: Intended Audience :: Science/Research
Classifier: License :: OSI Approved :: MIT License
Classifier: Operating System :: OS Independent
Classifier: Topic :: Scientific/Engineering :: Mathematics
Classifier: Topic :: Scientific/Engineering :: Physics
